pytest_xrayjira/__init__.py
pytest_xrayjira/constants.py
pytest_xrayjira/models.py
pytest_xrayjira/plugin.py
pytest_xrayjira/utils.py
pytest_xrayjira-1.0.2.dist-info/LICENSE
pytest_xrayjira-1.0.2.dist-info/METADATA
pytest_xrayjira-1.0.2.dist-info/WHEEL
pytest_xrayjira-1.0.2.dist-info/entry_points.txt
pytest_xrayjira-1.0.2.dist-info/top_level.txt
pytest_xrayjira-1.0.2.dist-info/RECORD
