Metadata-Version: 2.1
Name: pytest-xrayjira
Version: 1.0.2
Summary: UNKNOWN
Home-page: UNKNOWN
Author: Inbar Rose
Author-email: inbar.rose1@gmail.com
License: UNKNOWN
Platform: UNKNOWN
Classifier: Development Status :: 3 - Alpha
Classifier: Intended Audience :: Developers
Classifier: Topic :: Software Development :: Testing
Classifier: License :: OSI Approved :: MIT License
Classifier: Programming Language :: Python :: 3
Classifier: Programming Language :: Python :: 3.7
Classifier: Programming Language :: Python :: Implementation :: CPython
Requires-Python: >=3.7.4
Requires-Dist: pytest (==4.3.1)
Requires-Dist: requests (==2.21.0.2)
